mlvajra/README.md
mlvajra/__init__.py
mlvajra/__version__.py
mlvajra/Annotation/__init__.py
mlvajra/Annotation/textclf.py
mlvajra/Annotation/timeseries.py
mlvajra/Annotation/dashboard/app_layout.py
mlvajra/Annotation/dashboard/backend.py
mlvajra/Annotation/dashboard/callbacks.py
mlvajra/Annotation/dataPrograming/textAnnotation.py
mlvajra/Annotation/dataPrograming/tsAnnotation.py
mlvajra/activelearning/AL.py
mlvajra/activelearning/__init__.py
mlvajra/data/README.md
mlvajra/data/__init__.py
mlvajra/data/preprocess_config.ini
mlvajra/data/relationalDB.py
mlvajra/data/sparkutils.py
mlvajra/data/.mypy_cache/3.6/_importlib_modulespec.data.json
mlvajra/data/.mypy_cache/3.6/_importlib_modulespec.meta.json
mlvajra/data/.mypy_cache/3.6/abc.data.json
mlvajra/data/.mypy_cache/3.6/abc.meta.json
mlvajra/data/.mypy_cache/3.6/builtins.data.json
mlvajra/data/.mypy_cache/3.6/builtins.meta.json
mlvajra/data/.mypy_cache/3.6/codecs.data.json
mlvajra/data/.mypy_cache/3.6/codecs.meta.json
mlvajra/data/.mypy_cache/3.6/configparser.data.json
mlvajra/data/.mypy_cache/3.6/configparser.meta.json
mlvajra/data/.mypy_cache/3.6/functools.data.json
mlvajra/data/.mypy_cache/3.6/functools.meta.json
mlvajra/data/.mypy_cache/3.6/io.data.json
mlvajra/data/.mypy_cache/3.6/io.meta.json
mlvajra/data/.mypy_cache/3.6/mypy_extensions.data.json
mlvajra/data/.mypy_cache/3.6/mypy_extensions.meta.json
mlvajra/data/.mypy_cache/3.6/posix.data.json
mlvajra/data/.mypy_cache/3.6/posix.meta.json
mlvajra/data/.mypy_cache/3.6/string.data.json
mlvajra/data/.mypy_cache/3.6/string.meta.json
mlvajra/data/.mypy_cache/3.6/sys.data.json
mlvajra/data/.mypy_cache/3.6/sys.meta.json
mlvajra/data/.mypy_cache/3.6/threading.data.json
mlvajra/data/.mypy_cache/3.6/threading.meta.json
mlvajra/data/.mypy_cache/3.6/time.data.json
mlvajra/data/.mypy_cache/3.6/time.meta.json
mlvajra/data/.mypy_cache/3.6/types.data.json
mlvajra/data/.mypy_cache/3.6/types.meta.json
mlvajra/data/.mypy_cache/3.6/typing.data.json
mlvajra-0.1.4.3.dist-info/LICENSE
mlvajra-0.1.4.3.dist-info/WHEEL
mlvajra-0.1.4.3.dist-info/METADATA
mlvajra-0.1.4.3.dist-info/RECORD
