Metadata-Version: 2.1
Name: mlvajra
Version: 0.1.4.3
Summary: A Last weapon to save Data scientist
Home-page: https://github.com/rajagurunath/mlvajra
License: UNKNOWN
Author: gurunath
Author-email: gurunathrajagopal@gmail.com
Classifier: License :: OSI Approved :: Apache Software License
Project-URL: Documentation, https://mlvajra.readthedocs.io/en/latest/
